json_extended/__init__.py
json_extended-0.0.3.dist-info/LICENSE
json_extended-0.0.3.dist-info/METADATA
json_extended-0.0.3.dist-info/WHEEL
json_extended-0.0.3.dist-info/top_level.txt
json_extended-0.0.3.dist-info/RECORD
