Metadata-Version: 2.1
Name: json-extended
Version: 0.0.3
Summary: json module with ``datetime``, ``date`` and ``uuid`` support
Home-page: https://gitlab.com/point1304/json_extended
Author: Gyeongsu Yim
Author-email: point1304@gmail.com
License: UNKNOWN
Platform: UNKNOWN
Classifier: Programming Language :: Python :: 3
Classifier: License :: OSI Approved :: MIT License
Classifier: Operating System :: OS Independent
Requires-Python: >=3.6
